toffee_test/__init__.py
toffee_test/__version.py
toffee_test/markers.py
toffee_test/plugin.py
toffee_test/reporter.py
toffee_test/request.py
toffee_test/testcase.py
toffee_test/utils.py
toffee_test/templates/html/README.md
toffee_test/templates/html/base.html
toffee_test/templates/html/index.html
toffee_test/templates/html/module.html
toffee_test/templates/html/normalize.css
toffee_test/templates/html/style.css
toffee_test/templates/html/test.html
toffee_test/templates/html/toffee.html
toffee_test/templates/html/icons/arrow.svg
toffee_test/templates/html/icons/nok.svg
toffee_test/templates/html/icons/ok.svg
toffee_test/templates/html/icons/skip.svg
toffee_test-0.3.1.dist-info/METADATA
toffee_test-0.3.1.dist-info/WHEEL
toffee_test-0.3.1.dist-info/entry_points.txt
toffee_test-0.3.1.dist-info/licenses/LICENSE
toffee_test-0.3.1.dist-info/RECORD
