Metadata-Version: 2.4
Name: toffee-test
Version: 0.3.1
Summary: pytest plugin for toffee testing
Project-URL: Homepage, https://github.com/XS-MLVP/toffee-test
Project-URL: Source, https://github.com/XS-MLVP/toffee-test
Project-URL: Tracker, https://github.com/XS-MLVP/toffee-test/issues
License:                      木兰宽松许可证, 第2版
License-File: LICENSE
Classifier: Development Status :: 4 - Beta
Classifier: Framework :: Pytest
Classifier: Intended Audience :: Developers
Classifier: License :: OSI Approved :: Mulan Permissive Software License v2 (MulanPSL-2.0)
Classifier: Topic :: Scientific/Engineering :: Electronic Design Automation (EDA)
Requires-Python: >=3.8
Requires-Dist: filelock>=3.16.1
Requires-Dist: pytest-asyncio>=0.23.0
Requires-Dist: pytest-reporter-html1>=0.8.4
Requires-Dist: pytest-xdist>=3.5.0
Requires-Dist: pytest>=7.0.0
Requires-Dist: pytoffee>=0.2.3
